LegendSS/Data.py
LegendSS/__init__.py
LegendSS/generate.py
pyLegendSS-0.9.dist-info/LICENSE
pyLegendSS-0.9.dist-info/METADATA
pyLegendSS-0.9.dist-info/WHEEL
pyLegendSS-0.9.dist-info/top_level.txt
pyLegendSS-0.9.dist-info/RECORD
